msuaccalc/__init__.py
msuaccalc-0.1.0.dist-info/METADATA
msuaccalc-0.1.0.dist-info/WHEEL
msuaccalc-0.1.0.dist-info/RECORD
