Metadata-Version: 2.3
Name: msuaccalc
Version: 0.1.0
Summary: Decode Windows userAccountControl flags.
Author: CobblePot59
Author-email: cobblepot59@github.com
Requires-Python: >=3.9
Classifier: Programming Language :: Python :: 3
Classifier: Programming Language :: Python :: 3.9
Classifier: Programming Language :: Python :: 3.10
Classifier: Programming Language :: Python :: 3.11
Classifier: Programming Language :: Python :: 3.12
Classifier: Programming Language :: Python :: 3.13
